distals/__init__.py
distals/asjp.py
distals/conceptualizer.py
distals/distals.py
distals/glot_tree.py
distals/glottolog.py
distals/grambank.py
distals/l2v.py
distals/langname_utils.py
distals/linguameta.py
distals/phoible.py
distals/state_and_fate.py
distals/textbased.py
distals/wals.py
distals/wiki.py
distals-0.1.1.dist-info/LICENSE
distals-0.1.1.dist-info/METADATA
distals-0.1.1.dist-info/WHEEL
distals-0.1.1.dist-info/entry_points.txt
distals-0.1.1.dist-info/top_level.txt
distals-0.1.1.dist-info/RECORD
