Metadata-Version: 2.1
Name: distals
Version: 0.1.1
License-File: LICENSE
Requires-Dist: numpy >=2.0.0
Requires-Dist: scikit-learn >=1.0.0
Requires-Dist: scipy >=1.8.0
